servey/__init__.py
servey/__main__.py
servey/_version.py
servey/cors.py
servey/errors.py
servey/action/__init__.py
servey/action/action.py
servey/action/batch_invoker.py
servey/action/example.py
servey/action/util.py
servey/cache_control/__init__.py
servey/cache_control/cache_control_abc.py
servey/cache_control/cache_header.py
servey/cache_control/secure_hash_cache_control.py
servey/cache_control/timestamp_cache_control.py
servey/cache_control/ttl_cache_control.py
servey/event_channel/__init__.py
servey/event_channel/event_channel_abc.py
servey/event_channel/webhook_event_channel.py
servey/event_channel/background/__init__.py
servey/event_channel/background/background_action_channel.py
servey/event_channel/background/background_invoker_abc.py
servey/event_channel/websocket/__init__.py
servey/event_channel/websocket/event_filter_abc.py
servey/event_channel/websocket/websocket_event_channel.py
servey/event_channel/websocket/websocket_sender.py
servey/finder/__init__.py
servey/finder/action_finder_abc.py
servey/finder/event_channel_finder_abc.py
servey/finder/module_action_finder.py
servey/finder/module_event_channel_finder.py
servey/security/__init__.py
servey/security/authorization.py
servey/security/access_control/__init__.py
servey/security/access_control/access_control_abc.py
servey/security/access_control/allow_all.py
servey/security/access_control/allow_none.py
servey/security/access_control/scope_access_control.py
servey/security/authenticator/__init__.py
servey/security/authenticator/password_authenticator_abc.py
servey/security/authenticator/root_password_authenticator.py
servey/security/authorizer/__init__.py
servey/security/authorizer/authorizer_abc.py
servey/security/authorizer/authorizer_factory_abc.py
servey/security/authorizer/jwt_authorizer.py
servey/security/authorizer/jwt_authorizer_abc.py
servey/security/authorizer/jwt_authorizer_factory.py
servey/servey_aws/__init__.py
servey/servey_aws/aws_websocket_sender.py
servey/servey_aws/lambda_invoker.py
servey-5.0.0.dist-info/METADATA
servey-5.0.0.dist-info/WHEEL
servey-5.0.0.dist-info/RECORD
