Metadata-Version: 2.4
Name: servey
Version: 5.0.0
Summary: A better API layer for python
Project-URL: Repository, https://github.com/tofarr/servey
Author-email: Tim O'Farrell <tofarr@gmail.com>
License: MIT
Classifier: License :: OSI Approved :: MIT License
Classifier: Operating System :: OS Independent
Classifier: Programming Language :: Python :: 3
Requires-Python: >=3.10
Requires-Dist: cryptography~=46.0
Requires-Dist: injecty~=0.0
Requires-Dist: json-urley~=1.0
Requires-Dist: marshy~=6.0
Requires-Dist: pyjwt~=2.10
Requires-Dist: python-dateutil~=2.9
Requires-Dist: schemey~=8.0
Provides-Extra: all
Requires-Dist: black~=25.11; extra == 'all'
Requires-Dist: boto3~=1.42; extra == 'all'
Requires-Dist: celery~=5.6; extra == 'all'
Requires-Dist: jinja2~=3.1; extra == 'all'
Requires-Dist: pygments~=2.19; extra == 'all'
Requires-Dist: pylint~=4.0; extra == 'all'
Requires-Dist: pytest-cov~=7.0; extra == 'all'
Requires-Dist: pytest-xdist~=3.8; extra == 'all'
Requires-Dist: pytest~=9.0; extra == 'all'
Requires-Dist: python-multipart~=0.0; extra == 'all'
Requires-Dist: pyyaml~=6.0; extra == 'all'
Requires-Dist: requests~=2.32; extra == 'all'
Requires-Dist: ruamel-yaml~=0.18; extra == 'all'
Requires-Dist: starlette~=0.50; extra == 'all'
Requires-Dist: strawberry-graphql~=0.287; extra == 'all'
Requires-Dist: uvicorn[standard]~=0.38; extra == 'all'
Provides-Extra: dev
Requires-Dist: black~=25.11; extra == 'dev'
Requires-Dist: boto3~=1.42; extra == 'dev'
Requires-Dist: pylint~=4.0; extra == 'dev'
Requires-Dist: pytest-cov~=7.0; extra == 'dev'
Requires-Dist: pytest-xdist~=3.8; extra == 'dev'
Requires-Dist: pytest~=9.0; extra == 'dev'
Provides-Extra: scheduler
Requires-Dist: celery~=5.6; extra == 'scheduler'
Provides-Extra: server
Requires-Dist: pygments~=2.19; extra == 'server'
Requires-Dist: python-multipart~=0.0; extra == 'server'
Requires-Dist: requests~=2.32; extra == 'server'
Requires-Dist: starlette~=0.50; extra == 'server'
Requires-Dist: strawberry-graphql~=0.287; extra == 'server'
Requires-Dist: uvicorn[standard]~=0.38; extra == 'server'
Provides-Extra: serverless
Requires-Dist: pyyaml~=6.0; extra == 'serverless'
Requires-Dist: ruamel-yaml~=0.18; extra == 'serverless'
Requires-Dist: strawberry-graphql~=0.287; extra == 'serverless'
Provides-Extra: web-page
Requires-Dist: jinja2~=3.1; extra == 'web-page'
